the_calc_pack_Pranav76/__init__.py
the_calc_pack_Pranav76/clk.py
the_calc_pack_Pranav76-0.0.4.dist-info/LICENSE.txt
the_calc_pack_Pranav76-0.0.4.dist-info/METADATA
the_calc_pack_Pranav76-0.0.4.dist-info/WHEEL
the_calc_pack_Pranav76-0.0.4.dist-info/top_level.txt
the_calc_pack_Pranav76-0.0.4.dist-info/RECORD
