Metadata-Version: 2.1
Name: the-calc-pack-Pranav76
Version: 0.0.4
Summary: This package helps you to carry out basic arithmetic operations
Author-email: Pranav Gore <gpranav657@gmail.com>
Classifier: Programming Language :: Python :: 3
Classifier: License :: OSI Approved :: MIT License
Classifier: Operating System :: OS Independent
Requires-Python: >=3.7
License-File: LICENSE.txt
